setup.py
django_env_server/__init__.py
django_env_server.egg-info/PKG-INFO
django_env_server.egg-info/SOURCES.txt
django_env_server.egg-info/dependency_links.txt
django_env_server.egg-info/requires.txt
django_env_server.egg-info/top_level.txt
django_env_server/management/__init__.py
django_env_server/management/commands/__init__.py
django_env_server/management/commands/envserver.py
test/test.py