Metadata-Version: 1.0
Name: django-env-server
Version: 0.0.1
Summary: Load environment variables into the Django development server
Home-page: https://github.com/mcfstr/django-env-server
Author: Matt Foster
Author-email: matt@mcfstr.com
License: MIT
Platform: UNKNOWN
